{
  "updated_at": "2024-04-14T11:20:05.014Z",
  "date_range_all_from": "2023-04-16T00:11:48.000Z",
  "date_range_all_to": "2024-04-13T11:11:22.000Z",
  "date_range_from": "2024-03-15T00:00:00.000Z",
  "date_range_to": "2024-04-13T23:59:59.999Z",
  "parseWarnings": 12,
  "_comment": "auto generated; do not manually modify",
  "_time_dsc": "all times are in seconds",
  "unit_time_stats": {
    "first_unit_reaction": {
      "sum": 5638,
      "mean": 131,
      "q1": 59,
      "median": 109,
      "q3": 138,
      "min": 9,
      "max": 780
    },
    "travel": {
      "sum": 23308,
      "mean": 486,
      "q1": 232,
      "median": 387,
      "q3": 659,
      "min": 106,
      "max": 1367
    },
    "to_scene": {
      "sum": 38735,
      "mean": 791,
      "q1": 362,
      "median": 630,
      "q3": 892,
      "min": 210,
      "max": 2827
    },
    "on_scene": {
      "sum": 96195,
      "mean": 1963,
      "q1": 972,
      "median": 1476,
      "q3": 2667,
      "min": 24,
      "max": 7478
    }
  },
  "personnel_stats": {
    "time_on_incidents": {
      "sum": 255061,
      "mean": 5427,
      "q1": 1360,
      "median": 3878,
      "q3": 5422,
      "min": 70,
      "max": 63195
    },
    "num_per_incidents": {
      "mean": 2.4,
      "q1": 2,
      "median": 2,
      "q3": 3,
      "min": 0,
      "max": 9
    },
    "num_unique_responders": 19
  },
  "region_stats": {
    "central": {
      "incident_types": {
        "medical_rescue": 13,
        "fire": 4,
        "downgraded": 6,
        "cancelled": 8,
        "other": 0
      },
      "num_incidents": 31,
      "unit_travel_time": {
        "sum": 7366,
        "mean": 295,
        "q1": 179,
        "median": 249,
        "q3": 379,
        "min": 106,
        "max": 665
      }
    },
    "north": {
      "incident_types": {
        "medical_rescue": 5,
        "fire": 0,
        "downgraded": 1,
        "cancelled": 2,
        "other": 0
      },
      "num_incidents": 8,
      "unit_travel_time": {
        "sum": 6126,
        "mean": 875,
        "q1": 764,
        "median": 912,
        "q3": 1056,
        "min": 407,
        "max": 1169
      }
    },
    "south": {
      "incident_types": {
        "medical_rescue": 2,
        "fire": 4,
        "downgraded": 1,
        "cancelled": 0,
        "other": 0
      },
      "num_incidents": 7,
      "unit_travel_time": {
        "sum": 7866,
        "mean": 605,
        "q1": 592,
        "median": 598,
        "q3": 689,
        "min": 252,
        "max": 1200
      }
    },
    "other": {
      "incident_types": {
        "medical_rescue": 0,
        "fire": 0,
        "downgraded": 1,
        "cancelled": 0,
        "other": 0
      },
      "num_incidents": 1,
      "unit_travel_time": {
        "sum": 1950,
        "mean": 650,
        "q1": 292,
        "median": 384,
        "q3": 876,
        "min": 199,
        "max": 1367
      }
    }
  },
  "incident_stats": {
    "types": {
      "medical_rescue": 20,
      "fire": 8,
      "downgraded": 9,
      "cancelled": 10,
      "other": 0
    },
    "num_incidents_last_365_days": 661,
    "num_incidents": 47,
    "num_daytime_incidents": 31,
    "num_nighttime_incidents": 16,
    "incident_times": {
      "sum": 92109,
      "mean": 1960,
      "q1": 680,
      "median": 1721,
      "q3": 2553,
      "min": 35,
      "max": 9055
    },
    "num_overlapping_incidents": 8,
    "num_per_day": {
      "sum": 47,
      "mean": 2,
      "q1": 1,
      "median": 1,
      "q3": 2,
      "min": 0,
      "max": 3
    }
  },
  "apparatus_stats": {
    "num_per_incident": {
      "mean": 1.3,
      "q1": 1,
      "median": 1,
      "q3": 1,
      "min": 1,
      "max": 5
    },
    "num_unique_used": 8
  }
}