{
  "updated_at": "2023-02-10T09:14:32.341Z",
  "date_range_all_from": "2022-02-10T17:04:33.000Z",
  "date_range_all_to": "2023-02-07T09:57:53.000Z",
  "date_range_from": "2023-01-09T00:00:00.000Z",
  "date_range_to": "2023-02-07T23:59:59.999Z",
  "parseWarnings": 24,
  "_comment": "auto generated; do not manually modify",
  "_time_dsc": "all times are in seconds",
  "unit_time_stats": {
    "first_unit_reaction": {
      "sum": 5231,
      "mean": 97,
      "q1": 51,
      "median": 78,
      "q3": 111,
      "min": 9,
      "max": 418
    },
    "travel": {
      "sum": 22031,
      "mean": 501,
      "q1": 177,
      "median": 350,
      "q3": 659,
      "min": 71,
      "max": 3699
    },
    "to_scene": {
      "sum": 26636,
      "mean": 579,
      "q1": 284,
      "median": 397,
      "q3": 656,
      "min": 52,
      "max": 3746
    },
    "on_scene": {
      "sum": 48625,
      "mean": 1081,
      "q1": 406,
      "median": 879,
      "q3": 1684,
      "min": 23,
      "max": 3089
    }
  },
  "personnel_stats": {
    "time_on_incidents": {
      "sum": 188879,
      "mean": 3096,
      "q1": 1366,
      "median": 2492,
      "q3": 4430,
      "min": 384,
      "max": 11049
    },
    "num_per_incidents": {
      "mean": 2.3,
      "q1": 2,
      "median": 2,
      "q3": 2,
      "min": 1,
      "max": 10
    },
    "num_unique_responders": 20
  },
  "region_stats": {
    "central": {
      "incident_types": {
        "medical_rescue": 30,
        "fire": 0,
        "downgraded": 6,
        "cancelled": 11,
        "other": 0
      },
      "num_incidents": 47,
      "unit_travel_time": {
        "sum": 15529,
        "mean": 420,
        "q1": 170,
        "median": 318,
        "q3": 408,
        "min": 71,
        "max": 3699
      }
    },
    "south": {
      "incident_types": {
        "medical_rescue": 1,
        "fire": 0,
        "downgraded": 2,
        "cancelled": 3,
        "other": 0
      },
      "num_incidents": 6,
      "unit_travel_time": {
        "sum": 2389,
        "mean": 796,
        "q1": 598,
        "median": 951,
        "q3": 1073,
        "min": 244,
        "max": 1194
      }
    },
    "north": {
      "incident_types": {
        "medical_rescue": 3,
        "fire": 0,
        "downgraded": 1,
        "cancelled": 4,
        "other": 0
      },
      "num_incidents": 8,
      "unit_travel_time": {
        "sum": 4113,
        "mean": 1028,
        "q1": 946,
        "median": 1030,
        "q3": 1112,
        "min": 895,
        "max": 1159
      }
    }
  },
  "incident_stats": {
    "types": {
      "medical_rescue": 34,
      "fire": 0,
      "downgraded": 9,
      "cancelled": 18,
      "other": 0
    },
    "num_incidents_last_365_days": 1016,
    "num_incidents": 61,
    "num_daytime_incidents": 42,
    "num_nighttime_incidents": 19,
    "incident_times": {
      "sum": 85965,
      "mean": 1409,
      "q1": 681,
      "median": 1188,
      "q3": 1912,
      "min": 192,
      "max": 4135
    },
    "num_overlapping_incidents": 2,
    "num_per_day": {
      "sum": 61,
      "mean": 2,
      "q1": 1,
      "median": 2,
      "q3": 2,
      "min": 0,
      "max": 5
    }
  },
  "apparatus_stats": {
    "num_per_incident": {
      "mean": 1.1,
      "q1": 1,
      "median": 1,
      "q3": 1,
      "min": 1,
      "max": 4
    },
    "num_unique_used": 9
  }
}