{
  "updated_at": "2024-04-03T09:12:26.140Z",
  "date_range_all_from": "2023-04-04T14:29:08.000Z",
  "date_range_all_to": "2024-03-31T18:47:03.000Z",
  "date_range_from": "2024-03-02T00:00:00.000Z",
  "date_range_to": "2024-03-31T23:59:59.999Z",
  "parseWarnings": 7,
  "_comment": "auto generated; do not manually modify",
  "_time_dsc": "all times are in seconds",
  "unit_time_stats": {
    "first_unit_reaction": {
      "sum": 3709,
      "mean": 120,
      "q1": 69,
      "median": 109,
      "q3": 126,
      "min": 9,
      "max": 460
    },
    "travel": {
      "sum": 13908,
      "mean": 464,
      "q1": 198,
      "median": 313,
      "q3": 663,
      "min": 131,
      "max": 1144
    },
    "to_scene": {
      "sum": 17845,
      "mean": 576,
      "q1": 312,
      "median": 432,
      "q3": 779,
      "min": 210,
      "max": 1190
    },
    "on_scene": {
      "sum": 42972,
      "mean": 1386,
      "q1": 671,
      "median": 1126,
      "q3": 1762,
      "min": 24,
      "max": 3756
    }
  },
  "personnel_stats": {
    "time_on_incidents": {
      "sum": 133917,
      "mean": 3939,
      "q1": 1788,
      "median": 4158,
      "q3": 5291,
      "min": 70,
      "max": 11595
    },
    "num_per_incidents": {
      "mean": 2.1,
      "q1": 2,
      "median": 2,
      "q3": 2,
      "min": 1,
      "max": 3
    },
    "num_unique_responders": 12
  },
  "region_stats": {
    "north": {
      "incident_types": {
        "medical_rescue": 3,
        "fire": 1,
        "downgraded": 1,
        "cancelled": 0,
        "other": 1
      },
      "num_incidents": 6,
      "unit_travel_time": {
        "sum": 6179,
        "mean": 883,
        "q1": 864,
        "median": 955,
        "q3": 1095,
        "min": 163,
        "max": 1144
      }
    },
    "central": {
      "incident_types": {
        "medical_rescue": 10,
        "fire": 2,
        "downgraded": 6,
        "cancelled": 6,
        "other": 0
      },
      "num_incidents": 24,
      "unit_travel_time": {
        "sum": 5570,
        "mean": 293,
        "q1": 184,
        "median": 240,
        "q3": 334,
        "min": 131,
        "max": 672
      }
    },
    "south": {
      "incident_types": {
        "medical_rescue": 1,
        "fire": 2,
        "downgraded": 1,
        "cancelled": 0,
        "other": 0
      },
      "num_incidents": 4,
      "unit_travel_time": {
        "sum": 2159,
        "mean": 540,
        "q1": 523,
        "median": 594,
        "q3": 611,
        "min": 314,
        "max": 657
      }
    }
  },
  "incident_stats": {
    "types": {
      "medical_rescue": 14,
      "fire": 5,
      "downgraded": 8,
      "cancelled": 6,
      "other": 1
    },
    "num_incidents_last_365_days": 659,
    "num_incidents": 34,
    "num_daytime_incidents": 24,
    "num_nighttime_incidents": 10,
    "incident_times": {
      "sum": 60994,
      "mean": 1794,
      "q1": 894,
      "median": 1702,
      "q3": 2408,
      "min": 35,
      "max": 4244
    },
    "num_overlapping_incidents": 2,
    "num_per_day": {
      "sum": 34,
      "mean": 1,
      "q1": 0,
      "median": 1,
      "q3": 2,
      "min": 0,
      "max": 3
    }
  },
  "apparatus_stats": {
    "num_per_incident": {
      "mean": 1,
      "q1": 1,
      "median": 1,
      "q3": 1,
      "min": 1,
      "max": 2
    },
    "num_unique_used": 3
  }
}