{
  "updated_at": "2022-04-10T09:14:27.855Z",
  "date_range_all_from": "2021-04-10T03:14:19.000Z",
  "date_range_all_to": "2022-04-09T05:13:23.000Z",
  "date_range_from": "2022-03-11T00:00:00.000Z",
  "date_range_to": "2022-04-09T23:59:59.999Z",
  "parseWarnings": 7,
  "_comment": "auto generated; do not manually modify",
  "_time_dsc": "all times are in seconds",
  "unit_time_stats": {
    "first_unit_reaction": {
      "sum": 6525,
      "mean": 99,
      "q1": 68,
      "median": 95,
      "q3": 126,
      "min": 10,
      "max": 302
    },
    "travel": {
      "sum": 31953,
      "mean": 385,
      "q1": 175,
      "median": 314,
      "q3": 555,
      "min": 31,
      "max": 1193
    },
    "to_scene": {
      "sum": 45769,
      "mean": 551,
      "q1": 285,
      "median": 441,
      "q3": 741,
      "min": 76,
      "max": 1931
    },
    "on_scene": {
      "sum": 179892,
      "mean": 2142,
      "q1": 919,
      "median": 1322,
      "q3": 2253,
      "min": 123,
      "max": 12321
    }
  },
  "personnel_stats": {
    "time_on_incidents": {
      "sum": 526182,
      "mean": 7517,
      "q1": 2622,
      "median": 3668,
      "q3": 5192,
      "min": 558,
      "max": 136902
    },
    "num_per_incidents": {
      "mean": 2.7,
      "q1": 2,
      "median": 2,
      "q3": 2,
      "min": 1,
      "max": 17
    },
    "num_unique_responders": 30
  },
  "region_stats": {
    "central": {
      "incident_types": {
        "medical_rescue": 41,
        "fire": 6,
        "downgraded": 12,
        "cancelled": 3,
        "other": 0
      },
      "num_incidents": 62,
      "unit_travel_time": {
        "sum": 27157,
        "mean": 357,
        "q1": 173,
        "median": 297,
        "q3": 523,
        "min": 48,
        "max": 1193
      }
    },
    "north": {
      "incident_types": {
        "medical_rescue": 2,
        "fire": 0,
        "downgraded": 0,
        "cancelled": 1,
        "other": 0
      },
      "num_incidents": 3,
      "unit_travel_time": {
        "sum": 2729,
        "mean": 682,
        "q1": 473,
        "median": 790,
        "q3": 1000,
        "min": 31,
        "max": 1118
      }
    },
    "south": {
      "incident_types": {
        "medical_rescue": 3,
        "fire": 0,
        "downgraded": 0,
        "cancelled": 2,
        "other": 0
      },
      "num_incidents": 5,
      "unit_travel_time": {
        "sum": 2067,
        "mean": 689,
        "q1": 550,
        "median": 604,
        "q3": 786,
        "min": 495,
        "max": 968
      }
    }
  },
  "incident_stats": {
    "types": {
      "medical_rescue": 46,
      "fire": 6,
      "downgraded": 12,
      "cancelled": 6,
      "other": 0
    },
    "num_incidents_last_365_days": 1036,
    "num_incidents": 70,
    "num_daytime_incidents": 43,
    "num_nighttime_incidents": 27,
    "incident_times": {
      "sum": 147684,
      "mean": 2110,
      "q1": 1224,
      "median": 1673,
      "q3": 2349,
      "min": 279,
      "max": 13063
    },
    "num_overlapping_incidents": 7,
    "num_per_day": {
      "sum": 70,
      "mean": 2,
      "q1": 1,
      "median": 2,
      "q3": 3,
      "min": 0,
      "max": 5
    }
  },
  "apparatus_stats": {
    "num_per_incident": {
      "mean": 1.4,
      "q1": 1,
      "median": 1,
      "q3": 1,
      "min": 1,
      "max": 8
    },
    "num_unique_used": 12
  }
}