{
  "updated_at": "2022-06-06T09:15:26.775Z",
  "date_range_all_from": "2021-06-06T03:31:00.000Z",
  "date_range_all_to": "2022-06-05T16:29:23.000Z",
  "date_range_from": "2022-05-07T00:00:00.000Z",
  "date_range_to": "2022-06-05T23:59:59.999Z",
  "parseWarnings": 14,
  "_comment": "auto generated; do not manually modify",
  "_time_dsc": "all times are in seconds",
  "unit_time_stats": {
    "first_unit_reaction": {
      "sum": 7568,
      "mean": 96,
      "q1": 48,
      "median": 84,
      "q3": 121,
      "min": 6,
      "max": 780
    },
    "travel": {
      "sum": 42662,
      "mean": 496,
      "q1": 220,
      "median": 414,
      "q3": 669,
      "min": 71,
      "max": 1348
    },
    "to_scene": {
      "sum": 53414,
      "mean": 600,
      "q1": 332,
      "median": 554,
      "q3": 805,
      "min": 85,
      "max": 1471
    },
    "on_scene": {
      "sum": 169396,
      "mean": 1903,
      "q1": 769,
      "median": 1228,
      "q3": 2088,
      "min": 74,
      "max": 41897
    }
  },
  "personnel_stats": {
    "time_on_incidents": {
      "sum": 476641,
      "mean": 5608,
      "q1": 2606,
      "median": 4106,
      "q3": 6064,
      "min": 262,
      "max": 84988
    },
    "num_per_incidents": {
      "mean": 2.4,
      "q1": 2,
      "median": 2,
      "q3": 2,
      "min": 1,
      "max": 8
    },
    "num_unique_responders": 23
  },
  "region_stats": {
    "central": {
      "incident_types": {
        "medical_rescue": 35,
        "fire": 8,
        "downgraded": 10,
        "cancelled": 14,
        "other": 0
      },
      "num_incidents": 67,
      "unit_travel_time": {
        "sum": 26594,
        "mean": 391,
        "q1": 194,
        "median": 329,
        "q3": 533,
        "min": 71,
        "max": 1172
      }
    },
    "north": {
      "incident_types": {
        "medical_rescue": 6,
        "fire": 1,
        "downgraded": 2,
        "cancelled": 5,
        "other": 1
      },
      "num_incidents": 15,
      "unit_travel_time": {
        "sum": 13918,
        "mean": 928,
        "q1": 808,
        "median": 901,
        "q3": 1089,
        "min": 369,
        "max": 1348
      }
    },
    "south": {
      "incident_types": {
        "medical_rescue": 2,
        "fire": 0,
        "downgraded": 1,
        "cancelled": 0,
        "other": 0
      },
      "num_incidents": 3,
      "unit_travel_time": {
        "sum": 2150,
        "mean": 717,
        "q1": 629,
        "median": 655,
        "q3": 774,
        "min": 603,
        "max": 892
      }
    }
  },
  "incident_stats": {
    "types": {
      "medical_rescue": 43,
      "fire": 9,
      "downgraded": 13,
      "cancelled": 19,
      "other": 1
    },
    "num_incidents_last_365_days": 1037,
    "num_incidents": 85,
    "num_daytime_incidents": 57,
    "num_nighttime_incidents": 28,
    "incident_times": {
      "sum": 212496,
      "mean": 2500,
      "q1": 1225,
      "median": 1790,
      "q3": 2943,
      "min": 131,
      "max": 42494
    },
    "num_overlapping_incidents": 10,
    "num_per_day": {
      "sum": 85,
      "mean": 3,
      "q1": 2,
      "median": 3,
      "q3": 4,
      "min": 0,
      "max": 7
    }
  },
  "apparatus_stats": {
    "num_per_incident": {
      "mean": 1.2,
      "q1": 1,
      "median": 1,
      "q3": 1,
      "min": 1,
      "max": 4
    },
    "num_unique_used": 8
  }
}